epub_to_text/__init__.py
epub_to_text/__main__.py
epub_to_text/batch_processor.py
epub_to_text/cli.py
epub_to_text/converter.py
epub_to_text/extractor.py
epub_to_text/processor.py
epub_to_text/reader.py
epub_to_text/wrapper.py
epub_to_text-2.0.0.dist-info/METADATA
epub_to_text-2.0.0.dist-info/WHEEL
epub_to_text-2.0.0.dist-info/entry_points.txt
epub_to_text-2.0.0.dist-info/top_level.txt
epub_to_text-2.0.0.dist-info/RECORD
