Metadata-Version: 2.4
Name: epub-to-text
Version: 2.0.0
Summary: Professional EPUB to Text/Markdown/JSON converter with batch processing
Author-email: Your Name <mrthinh@live.com>
License: MIT
Project-URL: Homepage, https://github.com/thinh-vu/epub_to_text
Project-URL: Repository, https://github.com/thinh-vu/epub_to_text.git
Keywords: epub,converter,text,markdown,json,batch-processing
Classifier: Development Status :: 4 - Beta
Classifier: Intended Audience :: Developers
Classifier: License :: OSI Approved :: MIT License
Classifier: Programming Language :: Python :: 3.10
Classifier: Programming Language :: Python :: 3.11
Classifier: Programming Language :: Python :: 3.12
Classifier: Programming Language :: Python :: 3.13
Requires-Python: >=3.10
Requires-Dist: ebooklib>=0.17.1
Requires-Dist: beautifulsoup4>=4.9.0
Provides-Extra: dev
Requires-Dist: pytest>=6.0; extra == "dev"
Requires-Dist: black>=21.0; extra == "dev"
Requires-Dist: mypy>=0.900; extra == "dev"
Provides-Extra: advanced
Requires-Dist: jinja2>=3.0; extra == "advanced"
Requires-Dist: whoosh>=2.7; extra == "advanced"
Requires-Dist: spacy>=3.0; extra == "advanced"
